{"chunk_definitions":[{"row":23,"row_count":1,"visible":true,"expansion_state":0,"options":{"engine":"r","label":"unnamed-chunk-10"},"document_id":"F1B9D0C0","chunk_id":"c2lf45rqczy3h","chunk_label":"unnamed-chunk-1"},{"row":39,"row_count":1,"visible":true,"expansion_state":0,"options":{"engine":"r","label":"unnamed-chunk-11"},"document_id":"F1B9D0C0","chunk_id":"cq7jxrbrp6ksp","chunk_label":"unnamed-chunk-2"},{"row":50,"row_count":1,"visible":true,"expansion_state":0,"options":{"engine":"r","label":"unnamed-chunk-12"},"document_id":"F1B9D0C0","chunk_id":"cn2qeaf1ydb25","chunk_label":"unnamed-chunk-3"},{"row":69,"row_count":1,"visible":true,"expansion_state":0,"options":{"engine":"r","label":"unnamed-chunk-13"},"document_id":"F1B9D0C0","chunk_id":"czuevmyjwzqje","chunk_label":"unnamed-chunk-4"},{"row":85,"row_count":1,"visible":true,"expansion_state":0,"options":{"engine":"r","label":"unnamed-chunk-18"},"document_id":"F1B9D0C0","chunk_id":"c47xmyyacyv23","chunk_label":"unnamed-chunk-5"}],"doc_write_time":1630367164}